wgetx/__init__.py
wgetx/__main__.py
wgetx/args.py
wgetx/color.py
wgetx/download.py
wgetx/progress.py
wgetx/typedefs.py
wgetx/utils.py
wgetx-1.0.0.dist-info/METADATA
wgetx-1.0.0.dist-info/WHEEL
wgetx-1.0.0.dist-info/entry_points.txt
wgetx-1.0.0.dist-info/top_level.txt
wgetx-1.0.0.dist-info/RECORD
