Metadata-Version: 2.4
Name: wgetx
Version: 1.0.0
Summary: A modern CLI tool for downloading files with progress bars
Author-email: CELESTIFYX Team <celestifyx@gmail.com>
License-Expression: GPL-3.0-or-later
Project-URL: Homepage, https://gitlab.com/celestifyx/wgetx
Project-URL: Repository, https://gitlab.com/celestifyx/wgetx
Project-URL: Issues, https://gitlab.com/celestifyx/wgetx/-/issues
Keywords: download,wget,cli,progress,http
Classifier: Programming Language :: Python :: 3.12
Classifier: Operating System :: OS Independent
Requires-Python: >=3.12
